.editorconfig
.gitignore
.gitlab-ci.yml
LICENSE.rst
README.rst
build_docs.sh
example.plugin_changelog.json
example.plugin_package.json
publish.settings.sh
publish.sh
pyproject.toml
tsconfig.json
.idea/modules.xml
.idea/peek-plugin-base.iml
.idea/inspectionProfiles/Project_Default.xml
.idea/inspectionProfiles/profiles_settings.xml
examples/simple_subproc_usage/example_subproc_child_main.py
examples/simple_subproc_usage/example_subproc_class.py
examples/simple_subproc_usage/example_subproc_parent_main.py
peek_plugin_base/LoopingCallUtil.py
peek_plugin_base/PeekPlatformCommonHookABC.py
peek_plugin_base/PeekPlatformFileStorageHookABC.py
peek_plugin_base/PeekPlatformServerInfoHookABC.py
peek_plugin_base/PeekVortexUtil.py
peek_plugin_base/PlatformDependencyTest.py
peek_plugin_base/PluginCommonEntryHookABC.py
peek_plugin_base/PluginPackageFileConfig.py
peek_plugin_base/__init__.py
peek_plugin_base.egg-info/PKG-INFO
peek_plugin_base.egg-info/SOURCES.txt
peek_plugin_base.egg-info/dependency_links.txt
peek_plugin_base.egg-info/requires.txt
peek_plugin_base.egg-info/top_level.txt
peek_plugin_base/agent/PeekAgentPlatformHookABC.py
peek_plugin_base/agent/PeekPlatformAgentHttpHookABC.py
peek_plugin_base/agent/PluginAgentEntryHookABC.py
peek_plugin_base/agent/__init__.py
peek_plugin_base/client/PeekClientPlatformHookABC.py
peek_plugin_base/client/PeekPlatformFieldHttpHookABC.py
peek_plugin_base/client/PeekPlatformOfficeHttpHookABC.py
peek_plugin_base/client/PluginClientEntryHookABC.py
peek_plugin_base/client/__init__.py
peek_plugin_base/server/PeekPlatformAdminHttpHookABC.py
peek_plugin_base/server/PeekPlatformServerHttpHookABC.py
peek_plugin_base/server/PeekServerPlatformHookABC.py
peek_plugin_base/server/PluginLogicEntryHookABC.py
peek_plugin_base/server/PluginLogicEntryHookInheritenceTest.py
peek_plugin_base/server/PluginServerStorageEntryHookABC.py
peek_plugin_base/server/PluginServerWorkerEntryHookABC.py
peek_plugin_base/server/__init__.py
peek_plugin_base/simple_subproc/__init__.py
peek_plugin_base/simple_subproc/simple_subproc_child_protocol.py
peek_plugin_base/simple_subproc/simple_subproc_parent_protocol.py
