Metadata-Version: 2.4
Name: peek-plugin-base
Version: 5.0.4
Summary: Peek Plugin Base - dependencies that an Peek plugin needs
Author-email: Synerty <contact@synerty.com>
Project-URL: Homepage, https://github.com/Synerty/peek-plugin-base
Keywords: Peek,Python,Platform,synerty
License-File: LICENSE.rst
Requires-Dist: SQLAlchemy
Requires-Dist: alembic>=0.8.7
Requires-Dist: GeoAlchemy2
Requires-Dist: Twisted[conch,tls]
Requires-Dist: json-cfg-rw
Requires-Dist: vortexpy
Requires-Dist: pytmpdir
Requires-Dist: txhttputil
Requires-Dist: SOAPpy-py3>=0.52.30
Requires-Dist: wstools-py3>=0.54.2
Requires-Dist: txsuds-py3>=0.5.9
Requires-Dist: reactivex>=4.0.4
Requires-Dist: pytz
Requires-Dist: tzlocal
Requires-Dist: patch-ng>=1.17.4
Requires-Dist: setproctitle
Dynamic: license-file
